README
setup.py
bin/jw.py
jinja_wrapper/__init__.py
jinja_wrapper/base.py
jinja_wrapper/helpers.py
jinja_wrapper/settings.py
jinja_wrapper.egg-info/PKG-INFO
jinja_wrapper.egg-info/SOURCES.txt
jinja_wrapper.egg-info/dependency_links.txt
jinja_wrapper.egg-info/not-zip-safe
jinja_wrapper.egg-info/top_level.txt