Metadata-Version: 1.0
Name: jinja-wrapper
Version: 0.1
Summary: Wrapper for jinja
Home-page: https://github.com/kevinslin
Author: Kevin S Lin
Author-email: kevinslin8@gmail.com
License: MIT
Platform: UNKNOWN
